[
  {
    "id": 1,
    "name": "Wireless Bluetooth Headphones A",
    "imageSrc": "./images/headphones.jpg",
    "description": "High-quality wireless Bluetooth headphones with noise cancellation and 20 hours of battery life.",
    "price": 300
  },
  {
    "id": 2,
    "name": "Wireless Bluetooth Headphones B",
    "imageSrc": "./images/headphones.jpg",
    "description": "High-quality wireless Bluetooth headphones with noise cancellation and 20 hours of battery life.",
    "price": 300
  },
  {
    "id": 3,
    "name": "Wireless Bluetooth Headphones C",
    "imageSrc": "./images/headphones.jpg",
    "description": "High-quality wireless Bluetooth headphones with noise cancellation and 20 hours of battery life.",
    "price": 300
  },
  {
    "id": 4,
    "name": "Wireless Bluetooth Headphones D",
    "imageSrc": "./images/headphones.jpg",
    "description": "High-quality wireless Bluetooth headphones with noise cancellation and 20 hours of battery life.",
    "price": 300
  },
  {
    "id": 5,
    "name": "Wireless Bluetooth Headphones E",
    "imageSrc": "./images/headphones.jpg",
    "description": "High-quality wireless Bluetooth headphones with noise cancellation and 20 hours of battery life.",
    "price": 300
  },
  {
    "id": 6,
    "name": "Wireless Bluetooth Headphones F",
    "imageSrc": "./images/headphones.jpg",
    "description": "High-quality wireless Bluetooth headphones with noise cancellation and 20 hours of battery life.",
    "price": 300
  },
  {
    "id": 7,
    "name": "Wireless Bluetooth Headphones G",
    "imageSrc": "./images/headphones.jpg",
    "description": "High-quality wireless Bluetooth headphones with noise cancellation and 20 hours of battery life.",
    "price": 300
  },
  {
    "id": 8,
    "name": "Wireless Bluetooth Headphones H",
    "imageSrc": "./images/headphones.jpg",
    "description": "High-quality wireless Bluetooth headphones with noise cancellation and 20 hours of battery life.",
    "price": 300
  }
]
